soar/__init__.py
soar/body_forces.py
soar/module2.py
UOFC_SOAR-0.1.0.dist-info/LICENSE
UOFC_SOAR-0.1.0.dist-info/METADATA
UOFC_SOAR-0.1.0.dist-info/WHEEL
UOFC_SOAR-0.1.0.dist-info/top_level.txt
UOFC_SOAR-0.1.0.dist-info/RECORD
